result/UART_TX.v

module UART_TX 
  #(parameter CLKS_PER_BIT = 217)
  (
   input       i_Clock,
   input       i_TX_DV,
   input [7:0] i_TX_Byte, 
   output      o_TX_Active,
   output reg  o_TX_Serial,
   output      o_TX_Done
   );
 
  parameter IDLE         = 3'b000;
  parameter TX_START_BIT = 3'b001;
  parameter TX_DATA_BITS = 3'b010;
  parameter TX_STOP_BIT  = 3'b011;
  parameter CLEANUP      = 3'b100;
  
  reg [2:0] r_SM_Main     = 0;
  reg [7:0] r_Clock_Count = 0;
  reg [2:0] r_Bit_Index   = 0;
  reg [7:0] r_TX_Data     = 0;
  reg       r_TX_Done     = 0;
  reg       r_TX_Active   = 0;
    
  always @(posedge i_Clock)
  begin
      
    case (r_SM_Main)
      IDLE :
        begin
          o_TX_Serial   <= 1'b1;         
          r_TX_Done     <= 1'b0;
          r_Clock_Count <= 0;
          r_Bit_Index   <= 0;
          
          if (i_TX_DV == 1'b1)
          begin
            r_TX_Active <= 1'b1;
            r_TX_Data   <= i_TX_Byte;
            r_SM_Main   <= TX_START_BIT;
          end
          else
            r_SM_Main <= IDLE;
        end 
      
     
      TX_START_BIT :
        begin
          o_TX_Serial <= 1'b0;
          
      
          if (r_Clock_Count < CLKS_PER_BIT-1)
          begin
            r_Clock_Count <= r_Clock_Count + 1;
            r_SM_Main     <= TX_START_BIT;
          end
          else
          begin
            r_Clock_Count <= 0;
            r_SM_Main     <= TX_DATA_BITS;
          end
        end 
      
      
           
      TX_DATA_BITS :
        begin
          o_TX_Serial <= r_TX_Data[r_Bit_Index];
          
          if (r_Clock_Count < CLKS_PER_BIT-1)
          begin
            r_Clock_Count <= r_Clock_Count + 1;
            r_SM_Main     <= TX_DATA_BITS;
          end
          else
          begin
            r_Clock_Count <= 0;
            
       
            if (r_Bit_Index < 7)
            begin
              r_Bit_Index <= r_Bit_Index + 1;
              r_SM_Main   <= TX_DATA_BITS;
            end
            else
            begin
              r_Bit_Index <= 0;
              r_SM_Main   <= TX_STOP_BIT;
            end
          end 
        end
      
      
      
      TX_STOP_BIT :
        begin
          o_TX_Serial <= 1'b1;
         
          
          if (r_Clock_Count < CLKS_PER_BIT-1)
          begin
            r_Clock_Count <= r_Clock_Count + 1;
            r_SM_Main     <= TX_STOP_BIT;
          end
          else
          begin
            r_TX_Done     <= 1'b1;
            r_Clock_Count <= 0;
            r_SM_Main     <= CLEANUP;
            r_TX_Active   <= 1'b0;
          end 
        end 
      
      
      
      CLEANUP :
        begin
          r_TX_Done <= 1'b1;
          r_SM_Main <= IDLE;
        end
      
      
      default :
        r_SM_Main <= IDLE;
      
    endcase
  end
  
  assign o_TX_Active = r_TX_Active;
  assign o_TX_Done   = r_TX_Done;
  
endmodule

result/design.sv
//////////////////////////////////////////////////////////////////////
// File Downloaded from http://www.nandland.com
//////////////////////////////////////////////////////////////////////
// This file contains the UART Receiver.  This receiver is able to
// receive 8 bits of serial data, one start bit, one stop bit,
// and no parity bit.  When receive is complete o_rx_dv will be
// driven high for one clock cycle.
// 
// Set Parameter CLKS_PER_BIT as follows:
// CLKS_PER_BIT = (Frequency of i_Clock)/(Frequency of UART)
// Example: 25 MHz Clock, 115200 baud UART
// (25000000)/(115200) = 217
 
module UART_RX
  #(parameter CLKS_PER_BIT = 217)
  (
   input        i_Clock,
   input        i_RX_Serial,
   output       o_RX_DV,
   output [7:0] o_RX_Byte
   );
   
  parameter IDLE         = 3'b000;
  parameter RX_START_BIT = 3'b001;
  parameter RX_DATA_BITS = 3'b010;
  parameter RX_STOP_BIT  = 3'b011;
  parameter CLEANUP      = 3'b100;
  
  reg [7:0] r_Clock_Count = 0;
  reg [2:0] r_Bit_Index   = 0; //8 bits total
  reg [7:0] r_RX_Byte     = 0;
  reg       r_RX_DV       = 0;
  reg [2:0] r_SM_Main     = 0;
  
  
  // Purpose: Control RX state machine
  always @(posedge i_Clock)
  begin
      
    case (r_SM_Main)
      IDLE :
        begin
          r_RX_DV       <= 1'b0;
          r_Clock_Count <= 0;
          r_Bit_Index   <= 0;
          
          if (i_RX_Serial == 1'b0)          // Start bit detected
            r_SM_Main <= RX_START_BIT;
          else
            r_SM_Main <= IDLE;
        end
      
      // Check middle of start bit to make sure it's still low
      RX_START_BIT :
        begin
          if (r_Clock_Count == (CLKS_PER_BIT-1)/2)
          begin
            if (i_RX_Serial == 1'b0)
            begin
              r_Clock_Count <= 0;  // reset counter, found the middle
              r_SM_Main     <= RX_DATA_BITS;
            end
            else
              r_SM_Main <= IDLE;
          end
          else
          begin
            r_Clock_Count <= r_Clock_Count + 1;
            r_SM_Main     <= RX_START_BIT;
          end
        end // case: RX_START_BIT
      
      
      // Wait CLKS_PER_BIT-1 clock cycles to sample serial data
      RX_DATA_BITS :
        begin
          if (r_Clock_Count < CLKS_PER_BIT-1)
          begin
            r_Clock_Count <= r_Clock_Count + 1;
            r_SM_Main     <= RX_DATA_BITS;
          end
          else
          begin
            r_Clock_Count          <= 0;
            r_RX_Byte[r_Bit_Index] <= i_RX_Serial;
            
            // Check if we have received all bits
            if (r_Bit_Index < 7)
            begin
              r_Bit_Index <= r_Bit_Index + 1;
              r_SM_Main   <= RX_DATA_BITS;
            end
            else
            begin
              r_Bit_Index <= 0;
              r_SM_Main   <= RX_STOP_BIT;
            end
          end
        end // case: RX_DATA_BITS
      
      
      // Receive Stop bit.  Stop bit = 1
      RX_STOP_BIT :
        begin
          // Wait CLKS_PER_BIT-1 clock cycles for Stop bit to finish
          if (r_Clock_Count < CLKS_PER_BIT-1)
          begin
            r_Clock_Count <= r_Clock_Count + 1;
     	    r_SM_Main     <= RX_STOP_BIT;
          end
          else
          begin
       	    r_RX_DV       <= 1'b1;
            r_Clock_Count <= 0;
            r_SM_Main     <= CLEANUP;
          end
        end // case: RX_STOP_BIT
      
      
      // Stay here 1 clock
      CLEANUP :
        begin
          r_SM_Main <= IDLE;
          r_RX_DV   <= 1'b0;
        end
      
      
      default :
        r_SM_Main <= IDLE;
      
    endcase
  end    
  
  assign o_RX_DV   = r_RX_DV;
  assign o_RX_Byte = r_RX_Byte;
  
endmodule // UART_RX

result/testbench.sv

`timescale 1ns/10ps

`include "UART_TX.v"

module UART_TB ();

 
 
  parameter c_CLOCK_PERIOD_NS = 40;
  parameter c_CLKS_PER_BIT    = 217;
  parameter c_BIT_PERIOD      = 8600;
  
  reg r_Clock = 0;
  reg r_TX_DV = 0;
  wire w_TX_Active, w_UART_Line;
  wire w_TX_Serial;
  reg [7:0] r_TX_Byte = 0;
  wire [7:0] w_RX_Byte;

  UART_RX #(.CLKS_PER_BIT(c_CLKS_PER_BIT)) UART_RX_Inst
    (.i_Clock(r_Clock),
     .i_RX_Serial(w_UART_Line),
     .o_RX_DV(w_RX_DV),
     .o_RX_Byte(w_RX_Byte)
     );
  
  UART_TX #(.CLKS_PER_BIT(c_CLKS_PER_BIT)) UART_TX_Inst
    (.i_Clock(r_Clock),
     .i_TX_DV(r_TX_DV),
     .i_TX_Byte(r_TX_Byte),
     .o_TX_Active(w_TX_Active),
     .o_TX_Serial(w_TX_Serial),
     .o_TX_Done()
     );

  assign w_UART_Line = w_TX_Active ? w_TX_Serial : 1'b1;
    
  always
    #(c_CLOCK_PERIOD_NS/2) r_Clock <= !r_Clock;
  
 
  initial
    begin
     
      @(posedge r_Clock);
      @(posedge r_Clock);
      r_TX_DV   <= 1'b1;
      r_TX_Byte <= 8'h3F;
      @(posedge r_Clock);
      r_TX_DV <= 1'b0;

   
      @(posedge w_RX_DV);
      if (w_RX_Byte == 8'h3F)
        $display("Test Passed - Correct Byte Received");
      else
        $display("Test Failed - Incorrect Byte Received");
      $finish();
    end
  
  initial 
  begin
    
    $dumpfile("dump.vcd");
    $dumpvars(0);
  end
endmodule

result/dump.vcd
$date
Wed Aug 14 12:21:17 2024
$end
$version
Riviera-PRO Version 2023.04.112.8911
$end
$timescale
10 ps
$end

$scope module UART_TB $end
$var wire 1 ! w_TX_Active $end
$var wire 1 " w_UART_Line $end
$var wire 1 # w_TX_Serial $end
$var wire 8 $ w_RX_Byte [7:0] $end
$var wire 1 % w_RX_DV $end
$var reg 1 & r_Clock $end
$var reg 1 ' r_TX_DV $end
$var reg 8 ( r_TX_Byte [7:0] $end
$var parameter 32 ) c_CLOCK_PERIOD_NS [31:0] $end
$var parameter 32 * c_CLKS_PER_BIT [31:0] $end
$var parameter 32 + c_BIT_PERIOD [31:0] $end

$scope module UART_RX_Inst $end
$var wire 1 , i_Clock $end
$var wire 1 " i_RX_Serial $end
$var wire 1 % o_RX_DV $end
$var wire 8 $ o_RX_Byte [7:0] $end
$var reg 8 - r_Clock_Count [7:0] $end
$var reg 3 . r_Bit_Index [2:0] $end
$var reg 8 / r_RX_Byte [7:0] $end
$var reg 1 0 r_RX_DV $end
$var reg 3 1 r_SM_Main [2:0] $end
$var parameter 32 2 CLKS_PER_BIT [31:0] $end
$var parameter 3 3 IDLE [2:0] $end
$var parameter 3 4 RX_START_BIT [2:0] $end
$var parameter 3 5 RX_DATA_BITS [2:0] $end
$var parameter 3 6 RX_STOP_BIT [2:0] $end
$var parameter 3 7 CLEANUP [2:0] $end
$upscope $end


$scope module UART_TX_Inst $end
$var wire 1 , i_Clock $end
$var wire 1 8 i_TX_DV $end
$var wire 8 9 i_TX_Byte [7:0] $end
$var wire 1 ! o_TX_Active $end
$var wire 1 : o_TX_Done $end
$var reg 1 ; o_TX_Serial $end
$var reg 3 < r_SM_Main [2:0] $end
$var reg 8 = r_Clock_Count [7:0] $end
$var reg 3 > r_Bit_Index [2:0] $end
$var reg 8 ? r_TX_Data [7:0] $end
$var reg 1 @ r_TX_Done $end
$var reg 1 A r_TX_Active $end
$var parameter 32 B CLKS_PER_BIT [31:0] $end
$var parameter 3 C IDLE [2:0] $end
$var parameter 3 D TX_START_BIT [2:0] $end
$var parameter 3 E TX_DATA_BITS [2:0] $end
$var parameter 3 F TX_STOP_BIT [2:0] $end
$var parameter 3 G CLEANUP [2:0] $end
$upscope $end

$upscope $end

$enddefinitions $end
$dumpvars
0!
1"
x#
b0 $
0%
0&
0'
b0 (
b101000 )
b11011001 *
b10000110011000 +
0,
b0 -
b0 .
b0 /
00
b0 1
b11011001 2
b0 3
b1 4
b10 5
b11 6
b100 7
08
b0 9
0:
x;
b0 <
b0 =
b0 >
b0 ?
0@
0A
b11011001 B
b0 C
b1 D
b10 E
b11 F
b100 G
$end
#2000
1&
1,
1;
1#
#4000
0&
0,
#6000
1&
1,
1'
b111111 (
b111111 9
18
#8000
0&
0,
#10000
1&
1,
0'
1A
b111111 ?
b1 <
1!
08
#12000
0&
0,
#14000
1&
1,
0;
b1 =
0#
0"
#16000
0&
0,
#18000
1&
1,
b1 1
b10 =
#20000
0&
0,
#22000
1&
1,
b1 -
b11 =
#24000
0&
0,
#26000
1&
1,
b10 -
b100 =
#28000
0&
0,
#30000
1&
1,
b11 -
b101 =
#32000
0&
0,
#34000
1&
1,
b100 -
b110 =
#36000
0&
0,
#38000
1&
1,
b101 -
b111 =
#40000
0&
0,
#42000
1&
1,
b110 -
b1000 =
#44000
0&
0,
#46000
1&
1,
b111 -
b1001 =
#48000
0&
0,
#50000
1&
1,
b1000 -
b1010 =
#52000
0&
0,
#54000
1&
1,
b1001 -
b1011 =
#56000
0&
0,
#58000
1&
1,
b1010 -
b1100 =
#60000
0&
0,
#62000
1&
1,
b1011 -
b1101 =
#64000
0&
0,
#66000
1&
1,
b1100 -
b1110 =
#68000
0&
0,
#70000
1&
1,
b1101 -
b1111 =
#72000
0&
0,
#74000
1&
1,
b1110 -
b10000 =
#76000
0&
0,
#78000
1&
1,
b1111 -
b10001 =
#80000
0&
0,
#82000
1&
1,
b10000 -
b10010 =
#84000
0&
0,
#86000
1&
1,
b10001 -
b10011 =
#88000
0&
0,
#90000
1&
1,
b10010 -
b10100 =
#92000
0&
0,
#94000
1&
1,
b10011 -
b10101 =
#96000
0&
0,
#98000
1&
1,
b10100 -
b10110 =
#100000
0&
0,
#102000
1&
1,
b10101 -
b10111 =
#104000
0&
0,
#106000
1&
1,
b10110 -
b11000 =
#108000
0&
0,
#110000
1&
1,
b10111 -
b11001 =
#112000
0&
0,
#114000
1&
1,
b11000 -
b11010 =
#116000
0&
0,
#118000
1&
1,
b11001 -
b11011 =
#120000
0&
0,
#122000
1&
1,
b11010 -
b11100 =
#124000
0&
0,
#126000
1&
1,
b11011 -
b11101 =
#128000
0&
0,
#130000
1&
1,
b11100 -
b11110 =
#132000
0&
0,
#134000
1&
1,
b11101 -
b11111 =
#136000
0&
0,
#138000
1&
1,
b11110 -
b100000 =
#140000
0&
0,
#142000
1&
1,
b11111 -
b100001 =
#144000
0&
0,
#146000
1&
1,
b100000 -
b100010 =
#148000
0&
0,
#150000
1&
1,
b100001 -
b100011 =
#152000
0&
0,
#154000
1&
1,
b100010 -
b100100 =
#156000
0&
0,
#158000
1&
1,
b100011 -
b100101 =
#160000
0&
0,
#162000
1&
1,
b100100 -
b100110 =
#164000
0&
0,
#166000
1&
1,
b100101 -
b100111 =
#168000
0&
0,
#170000
1&
1,
b100110 -
b101000 =
#172000
0&
0,
#174000
1&
1,
b100111 -
b101001 =
#176000
0&
0,
#178000
1&
1,
b101000 -
b101010 =
#180000
0&
0,
#182000
1&
1,
b101001 -
b101011 =
#184000
0&
0,
#186000
1&
1,
b101010 -
b101100 =
#188000
0&
0,
#190000
1&
1,
b101011 -
b101101 =
#192000
0&
0,
#194000
1&
1,
b101100 -
b101110 =
#196000
0&
0,
#198000
1&
1,
b101101 -
b101111 =
#200000
0&
0,
#202000
1&
1,
b101110 -
b110000 =
#204000
0&
0,
#206000
1&
1,
b101111 -
b110001 =
#208000
0&
0,
#210000
1&
1,
b110000 -
b110010 =
#212000
0&
0,
#214000
1&
1,
b110001 -
b110011 =
#216000
0&
0,
#218000
1&
1,
b110010 -
b110100 =
#220000
0&
0,
#222000
1&
1,
b110011 -
b110101 =
#224000
0&
0,
#226000
1&
1,
b110100 -
b110110 =
#228000
0&
0,
#230000
1&
1,
b110101 -
b110111 =
#232000
0&
0,
#234000
1&
1,
b110110 -
b111000 =
#236000
0&
0,
#238000
1&
1,
b110111 -
b111001 =
#240000
0&
0,
#242000
1&
1,
b111000 -
b111010 =
#244000
0&
0,
#246000
1&
1,
b111001 -
b111011 =
#248000
0&
0,
#250000
1&
1,
b111010 -
b111100 =
#252000
0&
0,
#254000
1&
1,
b111011 -
b111101 =
#256000
0&
0,
#258000
1&
1,
b111100 -
b111110 =
#260000
0&
0,
#262000
1&
1,
b111101 -
b111111 =
#264000
0&
0,
#266000
1&
1,
b111110 -
b1000000 =
#268000
0&
0,
#270000
1&
1,
b111111 -
b1000001 =
#272000
0&
0,
#274000
1&
1,
b1000000 -
b1000010 =
#276000
0&
0,
#278000
1&
1,
b1000001 -
b1000011 =
#280000
0&
0,
#282000
1&
1,
b1000010 -
b1000100 =
#284000
0&
0,
#286000
1&
1,
b1000011 -
b1000101 =
#288000
0&
0,
#290000
1&
1,
b1000100 -
b1000110 =
#292000
0&
0,
#294000
1&
1,
b1000101 -
b1000111 =
#296000
0&
0,
#298000
1&
1,
b1000110 -
b1001000 =
#300000
0&
0,
#302000
1&
1,
b1000111 -
b1001001 =
#304000
0&
0,
#306000
1&
1,
b1001000 -
b1001010 =
#308000
0&
0,
#310000
1&
1,
b1001001 -
b1001011 =
#312000
0&
0,
#314000
1&
1,
b1001010 -
b1001100 =
#316000
0&
0,
#318000
1&
1,
b1001011 -
b1001101 =
#320000
0&
0,
#322000
1&
1,
b1001100 -
b1001110 =
#324000
0&
0,
#326000
1&
1,
b1001101 -
b1001111 =
#328000
0&
0,
#330000
1&
1,
b1001110 -
b1010000 =
#332000
0&
0,
#334000
1&
1,
b1001111 -
b1010001 =
#336000
0&
0,
#338000
1&
1,
b1010000 -
b1010010 =
#340000
0&
0,
#342000
1&
1,
b1010001 -
b1010011 =
#344000
0&
0,
#346000
1&
1,
b1010010 -
b1010100 =
#348000
0&
0,
#350000
1&
1,
b1010011 -
b1010101 =
#352000
0&
0,
#354000
1&
1,
b1010100 -
b1010110 =
#356000
0&
0,
#358000
1&
1,
b1010101 -
b1010111 =
#360000
0&
0,
#362000
1&
1,
b1010110 -
b1011000 =
#364000
0&
0,
#366000
1&
1,
b1010111 -
b1011001 =
#368000
0&
0,
#370000
1&
1,
b1011000 -
b1011010 =
#372000
0&
0,
#374000
1&
1,
b1011001 -
b1011011 =
#376000
0&
0,
#378000
1&
1,
b1011010 -
b1011100 =
#380000
0&
0,
#382000
1&
1,
b1011011 -
b1011101 =
#384000
0&
0,
#386000
1&
1,
b1011100 -
b1011110 =
#388000
0&
0,
#390000
1&
1,
b1011101 -
b1011111 =
#392000
0&
0,
#394000
1&
1,
b1011110 -
b1100000 =
#396000
0&
0,
#398000
1&
1,
b1011111 -
b1100001 =
#400000
0&
0,
#402000
1&
1,
b1100000 -
b1100010 =
#404000
0&
0,
#406000
1&
1,
b1100001 -
b1100011 =
#408000
0&
0,
#410000
1&
1,
b1100010 -
b1100100 =
#412000
0&
0,
#414000
1&
1,
b1100011 -
b1100101 =
#416000
0&
0,
#418000
1&
1,
b1100100 -
b1100110 =
#420000
0&
0,
#422000
1&
1,
b1100101 -
b1100111 =
#424000
0&
0,
#426000
1&
1,
b1100110 -
b1101000 =
#428000
0&
0,
#430000
1&
1,
b1100111 -
b1101001 =
#432000
0&
0,
#434000
1&
1,
b1101000 -
b1101010 =
#436000
0&
0,
#438000
1&
1,
b1101001 -
b1101011 =
#440000
0&
0,
#442000
1&
1,
b1101010 -
b1101100 =
#444000
0&
0,
#446000
1&
1,
b1101011 -
b1101101 =
#448000
0&
0,
#450000
1&
1,
b1101100 -
b1101110 =
#452000
0&
0,
#454000
1&
1,
b0 -
b10 1
b1101111 =
#456000
0&
0,
#458000
1&
1,
b1 -
b1110000 =
#460000
0&
0,
#462000
1&
1,
b10 -
b1110001 =
#464000
0&
0,
#466000
1&
1,
b11 -
b1110010 =
#468000
0&
0,
#470000
1&
1,
b100 -
b1110011 =
#472000
0&
0,
#474000
1&
1,
b101 -
b1110100 =
#476000
0&
0,
#478000
1&
1,
b110 -
b1110101 =
#480000
0&
0,
#482000
1&
1,
b111 -
b1110110 =
#484000
0&
0,
#486000
1&
1,
b1000 -
b1110111 =
#488000
0&
0,
#490000
1&
1,
b1001 -
b1111000 =
#492000
0&
0,
#494000
1&
1,
b1010 -
b1111001 =
#496000
0&
0,
#498000
1&
1,
b1011 -
b1111010 =
#500000
0&
0,
#502000
1&
1,
b1100 -
b1111011 =
#504000
0&
0,
#506000
1&
1,
b1101 -
b1111100 =
#508000
0&
0,
#510000
1&
1,
b1110 -
b1111101 =
#512000
0&
0,
#514000
1&
1,
b1111 -
b1111110 =
#516000
0&
0,
#518000
1&
1,
b10000 -
b1111111 =
#520000
0&
0,
#522000
1&
1,
b10001 -
b10000000 =
#524000
0&
0,
#526000
1&
1,
b10010 -
b10000001 =
#528000
0&
0,
#530000
1&
1,
b10011 -
b10000010 =
#532000
0&
0,
#534000
1&
1,
b10100 -
b10000011 =
#536000
0&
0,
#538000
1&
1,
b10101 -
b10000100 =
#540000
0&
0,
#542000
1&
1,
b10110 -
b10000101 =
#544000
0&
0,
#546000
1&
1,
b10111 -
b10000110 =
#548000
0&
0,
#550000
1&
1,
b11000 -
b10000111 =
#552000
0&
0,
#554000
1&
1,
b11001 -
b10001000 =
#556000
0&
0,
#558000
1&
1,
b11010 -
b10001001 =
#560000
0&
0,
#562000
1&
1,
b11011 -
b10001010 =
#564000
0&
0,
#566000
1&
1,
b11100 -
b10001011 =
#568000
0&
0,
#570000
1&
1,
b11101 -
b10001100 =
#572000
0&
0,
#574000
1&
1,
b11110 -
b10001101 =
#576000
0&
0,
#578000
1&
1,
b11111 -
b10001110 =
#580000
0&
0,
#582000
1&
1,
b100000 -
b10001111 =
#584000
0&
0,
#586000
1&
1,
b100001 -
b10010000 =
#588000
0&
0,
#590000
1&
1,
b100010 -
b10010001 =
#592000
0&
0,
#594000
1&
1,
b100011 -
b10010010 =
#596000
0&
0,
#598000
1&
1,
b100100 -
b10010011 =
#600000
0&
0,
#602000
1&
1,
b100101 -
b10010100 =
#604000
0&
0,
#606000
1&
1,
b100110 -
b10010101 =
#608000
0&
0,
#610000
1&
1,
b100111 -
b10010110 =
#612000
0&
0,
#614000
1&
1,
b101000 -
b10010111 =
#616000
0&
0,
#618000
1&
1,
b101001 -
b10011000 =
#620000
0&
0,
#622000
1&
1,
b101010 -
b10011001 =
#624000
0&
0,
#626000
1&
1,
b101011 -
b10011010 =
#628000
0&
0,
#630000
1&
1,
b101100 -
b10011011 =
#632000
0&
0,
#634000
1&
1,
b101101 -
b10011100 =
#636000
0&
0,
#638000
1&
1,
b101110 -
b10011101 =
#640000
0&
0,
#642000
1&
1,
b101111 -
b10011110 =
#644000
0&
0,
#646000
1&
1,
b110000 -
b10011111 =
#648000
0&
0,
#650000
1&
1,
b110001 -
b10100000 =
#652000
0&
0,
#654000
1&
1,
b110010 -
b10100001 =
#656000
0&
0,
#658000
1&
1,
b110011 -
b10100010 =
#660000
0&
0,
#662000
1&
1,
b110100 -
b10100011 =
#664000
0&
0,
#666000
1&
1,
b110101 -
b10100100 =
#668000
0&
0,
#670000
1&
1,
b110110 -
b10100101 =
#672000
0&
0,
#674000
1&
1,
b110111 -
b10100110 =
#676000
0&
0,
#678000
1&
1,
b111000 -
b10100111 =
#680000
0&
0,
#682000
1&
1,
b111001 -
b10101000 =
#684000
0&
0,
#686000
1&
1,
b111010 -
b10101001 =
#688000
0&
0,
#690000
1&
1,
b111011 -
b10101010 =
#692000
0&
0,
#694000
1&
1,
b111100 -
b10101011 =
#696000
0&
0,
#698000
1&
1,
b111101 -
b10101100 =
#700000
0&
0,
#702000
1&
1,
b111110 -
b10101101 =
#704000
0&
0,
#706000
1&
1,
b111111 -
b10101110 =
#708000
0&
0,
#710000
1&
1,
b1000000 -
b10101111 =
#712000
0&
0,
#714000
1&
1,
b1000001 -
b10110000 =
#716000
0&
0,
#718000
1&
1,
b1000010 -
b10110001 =
#720000
0&
0,
#722000
1&
1,
b1000011 -
b10110010 =
#724000
0&
0,
#726000
1&
1,
b1000100 -
b10110011 =
#728000
0&
0,
#730000
1&
1,
b1000101 -
b10110100 =
#732000
0&
0,
#734000
1&
1,
b1000110 -
b10110101 =
#736000
0&
0,
#738000
1&
1,
b1000111 -
b10110110 =
#740000
0&
0,
#742000
1&
1,
b1001000 -
b10110111 =
#744000
0&
0,
#746000
1&
1,
b1001001 -
b10111000 =
#748000
0&
0,
#750000
1&
1,
b1001010 -
b10111001 =
#752000
0&
0,
#754000
1&
1,
b1001011 -
b10111010 =
#756000
0&
0,
#758000
1&
1,
b1001100 -
b10111011 =
#760000
0&
0,
#762000
1&
1,
b1001101 -
b10111100 =
#764000
0&
0,
#766000
1&
1,
b1001110 -
b10111101 =
#768000
0&
0,
#770000
1&
1,
b1001111 -
b10111110 =
#772000
0&
0,
#774000
1&
1,
b1010000 -
b10111111 =
#776000
0&
0,
#778000
1&
1,
b1010001 -
b11000000 =
#780000
0&
0,
#782000
1&
1,
b1010010 -
b11000001 =
#784000
0&
0,
#786000
1&
1,
b1010011 -
b11000010 =
#788000
0&
0,
#790000
1&
1,
b1010100 -
b11000011 =
#792000
0&
0,
#794000
1&
1,
b1010101 -
b11000100 =
#796000
0&
0,
#798000
1&
1,
b1010110 -
b11000101 =
#800000
0&
0,
#802000
1&
1,
b1010111 -
b11000110 =
#804000
0&
0,
#806000
1&
1,
b1011000 -
b11000111 =
#808000
0&
0,
#810000
1&
1,
b1011001 -
b11001000 =
#812000
0&
0,
#814000
1&
1,
b1011010 -
b11001001 =
#816000
0&
0,
#818000
1&
1,
b1011011 -
b11001010 =
#820000
0&
0,
#822000
1&
1,
b1011100 -
b11001011 =
#824000
0&
0,
#826000
1&
1,
b1011101 -
b11001100 =
#828000
0&
0,
#830000
1&
1,
b1011110 -
b11001101 =
#832000
0&
0,
#834000
1&
1,
b1011111 -
b11001110 =
#836000
0&
0,
#838000
1&
1,
b1100000 -
b11001111 =
#840000
0&
0,
#842000
1&
1,
b1100001 -
b11010000 =
#844000
0&
0,
#846000
1&
1,
b1100010 -
b11010001 =
#848000
0&
0,
#850000
1&
1,
b1100011 -
b11010010 =
#852000
0&
0,
#854000
1&
1,
b1100100 -
b11010011 =
#856000
0&
0,
#858000
1&
1,
b1100101 -
b11010100 =
#860000
0&
0,
#862000
1&
1,
b1100110 -
b11010101 =
#864000
0&
0,
#866000
1&
1,
b1100111 -
b11010110 =
#868000
0&
0,
#870000
1&
1,
b1101000 -
b11010111 =
#872000
0&
0,
#874000
1&
1,
b1101001 -
b11011000 =
#876000
0&
0,
#878000
1&
1,
b1101010 -
b0 =
b10 <
#880000
0&
0,
#882000
1&
1,
b1101011 -
1;
b1 =
1#
1"
#884000
0&
0,
#886000
1&
1,
b1101100 -
b10 =
#888000
0&
0,
#890000
1&
1,
b1101101 -
b11 =
#892000
0&
0,
#894000
1&
1,
b1101110 -
b100 =
#896000
0&
0,
#898000
1&
1,
b1101111 -
b101 =
#900000
0&
0,
#902000
1&
1,
b1110000 -
b110 =
#904000
0&
0,
#906000
1&
1,
b1110001 -
b111 =
#908000
0&
0,
#910000
1&
1,
b1110010 -
b1000 =
#912000
0&
0,
#914000
1&
1,
b1110011 -
b1001 =
#916000
0&
0,
#918000
1&
1,
b1110100 -
b1010 =
#920000
0&
0,
#922000
1&
1,
b1110101 -
b1011 =
#924000
0&
0,
#926000
1&
1,
b1110110 -
b1100 =
#928000
0&
0,
#930000
1&
1,
b1110111 -
b1101 =
#932000
0&
0,
#934000
1&
1,
b1111000 -
b1110 =
#936000
0&
0,
#938000
1&
1,
b1111001 -
b1111 =
#940000
0&
0,
#942000
1&
1,
b1111010 -
b10000 =
#944000
0&
0,
#946000
1&
1,
b1111011 -
b10001 =
#948000
0&
0,
#950000
1&
1,
b1111100 -
b10010 =
#952000
0&
0,
#954000
1&
1,
b1111101 -
b10011 =
#956000
0&
0,
#958000
1&
1,
b1111110 -
b10100 =
#960000
0&
0,
#962000
1&
1,
b1111111 -
b10101 =
#964000
0&
0,
#966000
1&
1,
b10000000 -
b10110 =
#968000
0&
0,
#970000
1&
1,
b10000001 -
b10111 =
#972000
0&
0,
#974000
1&
1,
b10000010 -
b11000 =
#976000
0&
0,
#978000
1&
1,
b10000011 -
b11001 =
#980000
0&
0,
#982000
1&
1,
b10000100 -
b11010 =
#984000
0&
0,
#986000
1&
1,
b10000101 -
b11011 =
#988000
0&
0,
#990000
1&
1,
b10000110 -
b11100 =
#992000
0&
0,
#994000
1&
1,
b10000111 -
b11101 =
#996000
0&
0,
#998000
1&
1,
b10001000 -
b11110 =
#1000000
0&
0,
#1002000
1&
1,
b10001001 -
b11111 =
#1004000
0&
0,
#1006000
1&
1,
b10001010 -
b100000 =
#1008000
0&
0,
#1010000
1&
1,
b10001011 -
b100001 =
#1012000
0&
0,
#1014000
1&
1,
b10001100 -
b100010 =
#1016000
0&
0,
#1018000
1&
1,
b10001101 -
b100011 =
#1020000
0&
0,
#1022000
1&
1,
b10001110 -
b100100 =
#1024000
0&
0,
#1026000
1&
1,
b10001111 -
b100101 =
#1028000
0&
0,
#1030000
1&
1,
b10010000 -
b100110 =
#1032000
0&
0,
#1034000
1&
1,
b10010001 -
b100111 =
#1036000
0&
0,
#1038000
1&
1,
b10010010 -
b101000 =
#1040000
0&
0,
#1042000
1&
1,
b10010011 -
b101001 =
#1044000
0&
0,
#1046000
1&
1,
b10010100 -
b101010 =
#1048000
0&
0,
#1050000
1&
1,
b10010101 -
b101011 =
#1052000
0&
0,
#1054000
1&
1,
b10010110 -
b101100 =
#1056000
0&
0,
#1058000
1&
1,
b10010111 -
b101101 =
#1060000
0&
0,
#1062000
1&
1,
b10011000 -
b101110 =
#1064000
0&
0,
#1066000
1&
1,
b10011001 -
b101111 =
#1068000
0&
0,
#1070000
1&
1,
b10011010 -
b110000 =
#1072000
0&
0,
#1074000
1&
1,
b10011011 -
b110001 =
#1076000
0&
0,
#1078000
1&
1,
b10011100 -
b110010 =
#1080000
0&
0,
#1082000
1&
1,
b10011101 -
b110011 =
#1084000
0&
0,
#1086000
1&
1,
b10011110 -
b110100 =
#1088000
0&
0,
#1090000
1&
1,
b10011111 -
b110101 =
#1092000
0&
0,
#1094000
1&
1,
b10100000 -
b110110 =
#1096000
0&
0,
#1098000
1&
1,
b10100001 -
b110111 =
#1100000
0&
0,
#1102000
1&
1,
b10100010 -
b111000 =
#1104000
0&
0,
#1106000
1&
1,
b10100011 -
b111001 =
#1108000
0&
0,
#1110000
1&
1,
b10100100 -
b111010 =
#1112000
0&
0,
#1114000
1&
1,
b10100101 -
b111011 =
#1116000
0&
0,
#1118000
1&
1,
b10100110 -
b111100 =
#1120000
0&
0,
#1122000
1&
1,
b10100111 -
b111101 =
#1124000
0&
0,
#1126000
1&
1,
b10101000 -
b111110 =
#1128000
0&
0,
#1130000
1&
1,
b10101001 -
b111111 =
#1132000
0&
0,
#1134000
1&
1,
b10101010 -
b1000000 =
#1136000
0&
0,
#1138000
1&
1,
b10101011 -
b1000001 =
#1140000
0&
0,
#1142000
1&
1,
b10101100 -
b1000010 =
#1144000
0&
0,
#1146000
1&
1,
b10101101 -
b1000011 =
#1148000
0&
0,
#1150000
1&
1,
b10101110 -
b1000100 =
#1152000
0&
0,
#1154000
1&
1,
b10101111 -
b1000101 =
#1156000
0&
0,
#1158000
1&
1,
b10110000 -
b1000110 =
#1160000
0&
0,
#1162000
1&
1,
b10110001 -
b1000111 =
#1164000
0&
0,
#1166000
1&
1,
b10110010 -
b1001000 =
#1168000
0&
0,
